MANIFEST.in
setup.py
avi/__init__.py
avi/f5_converter/__init__.py
avi/f5_converter/config_patch.py
avi/f5_converter/conversion_util.py
avi/f5_converter/converter_constants.py
avi/f5_converter/f5_config_converter.py
avi/f5_converter/f5_converter.py
avi/f5_converter/f5_parser.py
avi/f5_converter/f5_v10_defaults.conf
avi/f5_converter/f5_v11_defaults.conf
avi/f5_converter/gr.json
avi/f5_converter/monitor_converter.py
avi/f5_converter/persistence_converter.py
avi/f5_converter/pool_converter.py
avi/f5_converter/profile_converter.py
avi/f5_converter/scp_util.py
avi/f5_converter/setup.py
avi/f5_converter/upload_config.py
avi/f5_converter/vs_converter.py
avi/f5_converter/output/panw_core.json
avi/f5_converter/output/panw_dmz.json
avi/f5_converter/output/10.90.117.120/input/.tmp1024dh.pem
avi/f5_converter/output/10.90.117.120/input/.tmp1024rsa.pem
avi/f5_converter/output/10.90.117.120/input/.tmp512dh.pem
avi/f5_converter/output/10.90.117.120/input/.tmp512rsa.pem
avi/f5_converter/output/10.90.117.120/input/.tmpecparam.pem
avi/f5_converter/output/10.90.117.120/input/CTO_bigip.conf
avi/f5_converter/output/10.90.117.120/input/base_monitors.conf
avi/f5_converter/output/10.90.117.120/input/bigip.conf
avi/f5_converter/output/10.90.117.120/input/bigip_gtm.conf
avi/f5_converter/output/10.90.117.120/input/ca-bundle.crt
avi/f5_converter/output/10.90.117.120/input/default.crt
avi/f5_converter/output/10.90.117.120/input/default.key
avi/f5_converter/output/10.90.117.120/input/dtca-bundle.crt
avi/f5_converter/output/10.90.117.120/input/dtca.crt
avi/f5_converter/output/10.90.117.120/input/dtca.key
avi/f5_converter/output/10.90.117.120/input/dtdi.crt
avi/f5_converter/output/10.90.117.120/input/dtdi.key
avi/f5_converter/output/10.90.117.120/input/f5-irule.crt
avi/f5_converter/output/10.90.117.120/input/profile_base.conf
avi/f5_converter/output/10.90.117.120/input/test2_bigip.conf
avi/f5_converter/output/10.90.117.120/input/test_bigip.conf
avif5converter.egg-info/PKG-INFO
avif5converter.egg-info/SOURCES.txt
avif5converter.egg-info/dependency_links.txt
avif5converter.egg-info/requires.txt
avif5converter.egg-info/top_level.txt
