Metadata-Version: 1.1
Name: avif5converter
Version: 16.3.6
Summary: Avi F5 Converter.
Home-page: http://avinetworks.com/
Author: Avi Networks
Author-email: support@avinetworks.com
License: UNKNOWN
Platform: UNKNOWN
Classifier: Operating System :: OS Independent
Classifier: Programming Language :: Python
Classifier: Programming Language :: Python :: 2.7
Classifier: Topic :: Internet :: WWW/HTTP
Classifier: Topic :: Internet :: WWW/HTTP :: Dynamic Content
